Metadata-Version: 1.0
Name: uploadlib
Version: 0.1.29
Summary: 上传器库，可以上传下载文件。
Home-page: https://code.xueersi.com
Author: Ruoyu Wang
Author-email: UNKNOWN
License: UNKNOWN
Platform: UNKNOWN
